{
  "_class": "group",
  "do_objectID": "73252876-62AC-4BB8-9B07-061AAD9C8DF2",
  "exportOptions": {
    "_class": "exportOptions",
    "do_objectID": "75BD45CD-340C-441F-AF1C-A25B9968C6F0",
    "exportFormats": [
    ],
    "includedLayerIds": [
    ],
    "layerOptions": 0,
    "shouldTrim": false
  },
  "frame": {
    "_class": "rect",
    "constrainProportions": false,
    "do_objectID": "7C6767B8-40C0-4077-8004-2A7E5F4902E4",
    "height": 16,
    "width": 295,
    "x": 274,
    "y": 47
  },
  "hasClickThrough": false,
  "isFlippedHorizontal": false,
  "isFlippedVertical": false,
  "isLocked": false,
  "isVisible": true,
  "layerListExpandedType": 0,
  "layers": [
    {
      "class": "text",
      "id": "427D22B2-328C-49D4-BC2C-43B5858237F0"
    }
  ],
  "name": "Group",
  "nameIsFixed": false,
  "resizingConstraint": 63,
  "resizingType": 0,
  "rotation": 0,
  "shouldBreakMaskChain": false,
  "style": {
    "_class": "style",
    "do_objectID": "7700E359-7B24-4898-AE3D-5F1EB092E0B7",
    "endDecorationType": 0,
    "miterLimit": 10,
    "startDecorationType": 0
  }
}