{
  "_class": "symbolInstance",
  "do_objectID": "00147754-2974-4200-9847-82ACD8EF7B0F",
  "exportOptions": {
    "_class": "exportOptions",
    "do_objectID": "47D657DE-2690-4302-9474-2C2B282191F4",
    "exportFormats": [
    ],
    "includedLayerIds": [
    ],
    "layerOptions": 0,
    "shouldTrim": false
  },
  "frame": {
    "_class": "rect",
    "constrainProportions": false,
    "do_objectID": "D7E7FC77-A7A4-491E-9CAE-CF4B1577B10C",
    "height": 66,
    "width": 120,
    "x": 143,
    "y": 1386
  },
  "horizontalSpacing": 0,
  "isFlippedHorizontal": false,
  "isFlippedVertical": false,
  "isLocked": false,
  "isVisible": true,
  "layerListExpandedType": 0,
  "name": "arrows/arrow 8.1 dotted",
  "nameIsFixed": false,
  "overrideValues": [
  ],
  "resizingConstraint": 63,
  "resizingType": 0,
  "rotation": 0,
  "scale": 1,
  "shouldBreakMaskChain": false,
  "style": {
    "_class": "style",
    "do_objectID": "6A4E07CC-CE83-485C-A7FC-1DB41EA452B6",
    "endDecorationType": 0,
    "miterLimit": 10,
    "startDecorationType": 0
  },
  "symbolID": "1FD26F06-0D9D-4E19-969B-BA939AA9B7B8",
  "verticalSpacing": 0
}