{
  "_class": "shapePath",
  "booleanOperation": -1,
  "do_objectID": "AF9DE09A-20A7-428C-822B-31ECF8FD9A0D",
  "edited": true,
  "exportOptions": {
    "_class": "exportOptions",
    "do_objectID": "C8E4A73B-B6E3-4789-A66E-745C4AA7A104",
    "exportFormats": [
    ],
    "includedLayerIds": [
    ],
    "layerOptions": 0,
    "shouldTrim": false
  },
  "frame": {
    "_class": "rect",
    "constrainProportions": false,
    "do_objectID": "6EF98503-3527-432C-8711-53234175A54F",
    "height": 16.09649723227593,
    "width": 3.815775547445127,
    "x": 0,
    "y": 0
  },
  "isClosed": true,
  "isFlippedHorizontal": false,
  "isFlippedVertical": false,
  "isLocked": false,
  "isVisible": true,
  "layerListExpandedType": 0,
  "name": "Path",
  "nameIsFixed": false,
  "pointRadiusBehaviour": 1,
  "points": [
    {
      "_class": "curvePoint",
      "cornerRadius": 0,
      "curveFrom": "{1, 0}",
      "curveMode": 1,
      "curveTo": "{1, 0}",
      "hasCurveFrom": false,
      "hasCurveTo": false,
      "point": "{1, 0}"
    },
    {
      "_class": "curvePoint",
      "cornerRadius": 0,
      "curveFrom": "{0.56507870466680576, 0.27827135940531106}",
      "curveMode": 1,
      "curveTo": "{0.56507870466680576, 0.27827135940531106}",
      "hasCurveFrom": false,
      "hasCurveTo": false,
      "point": "{0.56507870466680576, 0.27827135940531106}"
    },
    {
      "_class": "curvePoint",
      "cornerRadius": 0,
      "curveFrom": "{0, 1}",
      "curveMode": 1,
      "curveTo": "{0, 1}",
      "hasCurveFrom": false,
      "hasCurveTo": false,
      "point": "{0, 1}"
    },
    {
      "_class": "curvePoint",
      "cornerRadius": 0,
      "curveFrom": "{0.93766035642465839, 0.47845719968048511}",
      "curveMode": 1,
      "curveTo": "{0.93766035642465839, 0.47845719968048511}",
      "hasCurveFrom": false,
      "hasCurveTo": false,
      "point": "{0.93766035642465839, 0.47845719968048511}"
    }
  ],
  "resizingConstraint": 63,
  "resizingType": 0,
  "rotation": 0,
  "shouldBreakMaskChain": false
}