{
  "_class": "group",
  "do_objectID": "9CA3F31B-DFE7-49F4-9CDE-992E23892DDF",
  "exportOptions": {
    "_class": "exportOptions",
    "exportFormats": [
    ],
    "includedLayerIds": [
    ],
    "layerOptions": 0,
    "shouldTrim": false
  },
  "frame": {
    "_class": "rect",
    "constrainProportions": false,
    "height": 100,
    "width": 820,
    "x": 0,
    "y": 2456
  },
  "hasClickThrough": false,
  "isFlippedHorizontal": false,
  "isFlippedVertical": false,
  "isLocked": false,
  "isVisible": true,
  "layerListExpandedType": 0,
  "layers": [
    {
      "class": "shapeGroup",
      "id": "DD52D1AE-4A93-4961-BCFC-F17A72057D4D"
    },
    {
      "class": "text",
      "id": "F9196924-368A-4AF4-97EF-A067C5E1E284"
    },
    {
      "class": "text",
      "id": "28B88C9F-05BC-469E-A9FD-4466E50E8E33"
    },
    {
      "class": "text",
      "id": "2BE1DAB5-CF8A-44AD-A3C1-82408BDCB62C"
    }
  ],
  "name": "Text Style: 11",
  "nameIsFixed": false,
  "resizingConstraint": 63,
  "resizingType": 0,
  "rotation": 0,
  "shouldBreakMaskChain": false,
  "style": {
    "_class": "style",
    "endDecorationType": 0,
    "miterLimit": 10,
    "startDecorationType": 0
  }
}