{
  "_class": "shapeGroup",
  "clippingMaskMode": 0,
  "do_objectID": "2837DAA6-B8A7-47A9-B146-F1E4484FE569",
  "exportOptions": {
    "_class": "exportOptions",
    "do_objectID": "9E5AA0B2-0979-4C05-874F-859DDFE36BC9",
    "exportFormats": [
    ],
    "includedLayerIds": [
    ],
    "layerOptions": 0,
    "shouldTrim": false
  },
  "frame": {
    "_class": "rect",
    "constrainProportions": false,
    "do_objectID": "A9EC0C85-3696-475D-9876-BABFB35664E9",
    "height": 8.000000000000071,
    "width": 8.000000000000139,
    "x": 0,
    "y": 0
  },
  "hasClickThrough": false,
  "hasClippingMask": false,
  "isFlippedHorizontal": false,
  "isFlippedVertical": false,
  "isLocked": false,
  "isVisible": true,
  "layerListExpandedType": 1,
  "layers": [
    {
      "class": "rectangle",
      "id": "E1F4FE5F-856C-46B4-994A-5DE9262EFA51"
    }
  ],
  "name": "p",
  "nameIsFixed": false,
  "resizingConstraint": 63,
  "resizingType": 0,
  "rotation": 0,
  "shouldBreakMaskChain": false,
  "style": {
    "_class": "style",
    "do_objectID": "2B0A2B98-134F-4347-9EFB-32FC3F37C4E5",
    "endDecorationType": 0,
    "fills": [
      {
        "_class": "fill",
        "color": {
          "_class": "color",
          "alpha": 1,
          "blue": 0,
          "green": 0,
          "red": 0
        },
        "fillType": 0,
        "isEnabled": true,
        "noiseIndex": 0,
        "noiseIntensity": 0,
        "patternFillType": 1,
        "patternTileScale": 1
      }
    ],
    "miterLimit": 10,
    "startDecorationType": 0
  },
  "windingRule": 0
}