{
  "_class": "symbolInstance",
  "do_objectID": "A0E8E328-BF5A-48A4-A397-1578163DE185",
  "exportOptions": {
    "_class": "exportOptions",
    "do_objectID": "266D75B3-3F41-48FC-BBA9-07009160AE8E",
    "exportFormats": [
    ],
    "includedLayerIds": [
    ],
    "layerOptions": 0,
    "shouldTrim": false
  },
  "frame": {
    "_class": "rect",
    "constrainProportions": false,
    "do_objectID": "DE55C631-83C8-4651-A6C4-FEBB66F50D51",
    "height": 131.8811881188119,
    "width": 253.9905213270142,
    "x": 0,
    "y": 0
  },
  "horizontalSpacing": 0,
  "isFlippedHorizontal": false,
  "isFlippedVertical": false,
  "isLocked": false,
  "isVisible": true,
  "layerListExpandedType": 0,
  "name": "UI/Color/Flat/Blue",
  "nameIsFixed": false,
  "overrideValues": [
  ],
  "resizingConstraint": 63,
  "resizingType": 0,
  "rotation": 0,
  "scale": 1.32,
  "shouldBreakMaskChain": false,
  "style": {
    "_class": "style",
    "blur": {
      "_class": "blur",
      "center": "{0.5, 0.5}",
      "do_objectID": "D6C06051-D4E1-4617-9D4F-65AB0D762CF9",
      "isEnabled": false,
      "motionAngle": 0,
      "radius": 13.2,
      "type": 0
    },
    "do_objectID": "CA5F4BF8-C711-4938-917F-60B49CEC3B24",
    "endDecorationType": 0,
    "miterLimit": 10,
    "startDecorationType": 0
  },
  "symbolID": "C691C5A0-5614-4FE6-9E8A-098D33D80AD8",
  "verticalSpacing": 0
}