{
  "_class": "group",
  "do_objectID": "8BF7E745-DD19-49D0-9926-92F0F33CB9BF",
  "exportOptions": {
    "_class": "exportOptions",
    "do_objectID": "59D77D33-734D-44FC-905A-C2DBCED7A6A9",
    "exportFormats": [
    ],
    "includedLayerIds": [
    ],
    "layerOptions": 0,
    "shouldTrim": false
  },
  "frame": {
    "_class": "rect",
    "constrainProportions": false,
    "do_objectID": "C4B594A7-5F68-4731-A955-287FBF70594F",
    "height": 15,
    "width": 15,
    "x": 1138,
    "y": 36
  },
  "hasClickThrough": false,
  "isFlippedHorizontal": false,
  "isFlippedVertical": false,
  "isLocked": false,
  "isVisible": true,
  "layerListExpandedType": 2,
  "layers": [
    {
      "class": "shapeGroup",
      "id": "2014B53D-5928-425D-BBD9-735B4A63F73C"
    }
  ],
  "name": "search",
  "nameIsFixed": false,
  "resizingConstraint": 63,
  "resizingType": 0,
  "rotation": 0,
  "shouldBreakMaskChain": false,
  "style": {
    "_class": "style",
    "blur": {
      "_class": "blur",
      "center": "{0.5, 0.5}",
      "do_objectID": "9E67664D-FD61-4574-BC0F-5EFAD2D66493",
      "isEnabled": false,
      "motionAngle": 0,
      "radius": 0.28,
      "type": 0
    },
    "do_objectID": "3BA2E719-8E0D-4F9A-AD2A-3BCFA99E2CED",
    "endDecorationType": 0,
    "fills": [
      {
        "_class": "fill",
        "color": {
          "_class": "color",
          "alpha": 1,
          "blue": 0,
          "green": 0,
          "red": 0
        },
        "fillType": 0,
        "isEnabled": true,
        "noiseIndex": 0,
        "noiseIntensity": 0,
        "patternFillType": 1,
        "patternTileScale": 1
      }
    ],
    "miterLimit": 10,
    "startDecorationType": 0
  }
}