{
  "_class": "text",
  "attributedString": {
    "_class": "attributedString",
    "attributes": [
      {
        "_class": "stringAttribute",
        "attributes": {
          "MSAttributedStringColorAttribute": {
            "_class": "color",
            "alpha": 1,
            "blue": 0.2588235294117647,
            "green": 0.2196078431372549,
            "red": 0.1803921568627451
          },
          "MSAttributedStringFontAttribute": {
            "_class": "fontDescriptor",
            "attributes": {
              "name": "Play-Regular",
              "size": 14
            }
          },
          "paragraphStyle": {
            "_class": "paragraphStyle",
            "alignment": 0,
            "allowsDefaultTighteningForTruncation": 0
          }
        },
        "length": 8,
        "location": 0
      }
    ],
    "string": "17:13:33"
  },
  "automaticallyDrawOnUnderlyingPath": false,
  "do_objectID": "F59D50E3-6F60-4D35-8F63-924CD5BE6D54",
  "dontSynchroniseWithSymbol": false,
  "exportOptions": {
    "_class": "exportOptions",
    "do_objectID": "BBCCE17D-DCDD-488F-9518-59AEF98C6595",
    "exportFormats": [
    ],
    "includedLayerIds": [
    ],
    "layerOptions": 0,
    "shouldTrim": false
  },
  "frame": {
    "_class": "rect",
    "constrainProportions": false,
    "do_objectID": "7BD920E9-1040-4673-8FE8-62AF50BD32E5",
    "height": 16,
    "width": 56,
    "x": 0,
    "y": 80
  },
  "glyphBounds": "{{1, 3}, {54, 11}}",
  "isFlippedHorizontal": false,
  "isFlippedVertical": false,
  "isLocked": false,
  "isVisible": true,
  "layerListExpandedType": 0,
  "lineSpacingBehaviour": 2,
  "name": "17:13:33",
  "nameIsFixed": false,
  "resizingConstraint": 47,
  "resizingType": 0,
  "rotation": 0,
  "shouldBreakMaskChain": false,
  "style": {
    "_class": "style",
    "do_objectID": "1B530C2E-25C3-466B-A8D3-EE484E3415A5",
    "endDecorationType": 0,
    "miterLimit": 10,
    "sharedObjectID": "DCBC156E-0157-4C42-9705-A6977A6791E7",
    "startDecorationType": 0,
    "textStyle": {
      "_class": "textStyle",
      "do_objectID": "5474682A-BAC7-40D8-99F3-9A429E2143D7",
      "encodedAttributes": {
        "MSAttributedStringColorAttribute": {
          "_class": "color",
          "alpha": 1,
          "blue": 0.2588235294117647,
          "green": 0.2196078431372549,
          "red": 0.1803921568627451
        },
        "MSAttributedStringFontAttribute": {
          "_class": "fontDescriptor",
          "attributes": {
            "name": "Play-Regular",
            "size": 14
          }
        },
        "paragraphStyle": {
          "_class": "paragraphStyle",
          "alignment": 0,
          "allowsDefaultTighteningForTruncation": 0
        }
      },
      "verticalAlignment": 0
    }
  },
  "textBehaviour": 0
}