{
  "_class": "group",
  "do_objectID": "856C7F9A-5787-4AF5-8D6A-606C22E378C7",
  "exportOptions": {
    "_class": "exportOptions",
    "exportFormats": [
    ],
    "includedLayerIds": [
    ],
    "layerOptions": 0,
    "shouldTrim": false
  },
  "frame": {
    "_class": "rect",
    "constrainProportions": false,
    "height": 200,
    "width": 180,
    "x": 620,
    "y": 4200
  },
  "hasClickThrough": false,
  "isFlippedHorizontal": false,
  "isFlippedVertical": false,
  "isLocked": false,
  "isVisible": true,
  "layerListExpandedType": 0,
  "layers": [
    {
      "class": "shapeGroup",
      "id": "DEE11395-FDD5-43E2-8EED-108C3AD91C6B"
    },
    {
      "class": "shapeGroup",
      "id": "05E4E364-F107-42B0-B41D-B0B6BB4F4849"
    },
    {
      "class": "text",
      "id": "C074C6DC-0532-4A3D-B2E6-13175B10E30A"
    },
    {
      "class": "text",
      "id": "9982411D-4E6D-49E9-972E-D3D24628FABD"
    },
    {
      "class": "text",
      "id": "BA0E0E82-80A6-424F-8088-7658C0EF96D7"
    }
  ],
  "name": "Swatch: #919191",
  "nameIsFixed": false,
  "resizingConstraint": 63,
  "resizingType": 0,
  "rotation": 0,
  "shouldBreakMaskChain": false,
  "style": {
    "_class": "style",
    "endDecorationType": 0,
    "miterLimit": 10,
    "startDecorationType": 0
  }
}