{
  "_class": "text",
  "attributedString": {
    "_class": "attributedString",
    "attributes": [
      {
        "_class": "stringAttribute",
        "attributes": {
          "MSAttributedStringColorAttribute": {
            "_class": "color",
            "alpha": 1,
            "blue": 0.9372549019607843,
            "green": 0.5490196078431373,
            "red": 0.2627450980392157
          },
          "MSAttributedStringFontAttribute": {
            "_class": "fontDescriptor",
            "attributes": {
              "name": "Play-Regular",
              "size": 14
            }
          },
          "paragraphStyle": {
            "_class": "paragraphStyle",
            "alignment": 0,
            "allowsDefaultTighteningForTruncation": 0,
            "maximumLineHeight": 21,
            "minimumLineHeight": 21
          }
        },
        "length": 5,
        "location": 0
      }
    ],
    "string": "3 BTC"
  },
  "automaticallyDrawOnUnderlyingPath": false,
  "do_objectID": "983EF346-E27F-49A6-B7D1-378755169141",
  "dontSynchroniseWithSymbol": false,
  "exportOptions": {
    "_class": "exportOptions",
    "do_objectID": "8BFA0214-4425-4F09-856C-E15927793D3E",
    "exportFormats": [
    ],
    "includedLayerIds": [
    ],
    "layerOptions": 0,
    "shouldTrim": false
  },
  "frame": {
    "_class": "rect",
    "constrainProportions": false,
    "do_objectID": "5A96AAFF-3820-49CB-BAE0-5208FF2421EE",
    "height": 21,
    "width": 37,
    "x": 0,
    "y": 350
  },
  "glyphBounds": "{{1, 6}, {35, 11}}",
  "isFlippedHorizontal": false,
  "isFlippedVertical": false,
  "isLocked": false,
  "isVisible": true,
  "layerListExpandedType": 0,
  "lineSpacingBehaviour": 2,
  "name": "3 BTC",
  "nameIsFixed": false,
  "resizingConstraint": 47,
  "resizingType": 0,
  "rotation": 0,
  "shouldBreakMaskChain": false,
  "style": {
    "_class": "style",
    "do_objectID": "390505C8-FDA7-4C06-900B-DB64BC936E2D",
    "endDecorationType": 0,
    "miterLimit": 10,
    "sharedObjectID": "38EF7C77-BC59-487B-AC5D-CB84CF9EC462",
    "startDecorationType": 0,
    "textStyle": {
      "_class": "textStyle",
      "do_objectID": "6BA907AE-0287-45E6-88A1-B73C80F2FECC",
      "encodedAttributes": {
        "MSAttributedStringColorAttribute": {
          "_class": "color",
          "alpha": 1,
          "blue": 0.9372549019607843,
          "green": 0.5490196078431373,
          "red": 0.2627450980392157
        },
        "MSAttributedStringFontAttribute": {
          "_class": "fontDescriptor",
          "attributes": {
            "name": "Play-Regular",
            "size": 14
          }
        },
        "paragraphStyle": {
          "_class": "paragraphStyle",
          "alignment": 0,
          "allowsDefaultTighteningForTruncation": 0,
          "maximumLineHeight": 21,
          "minimumLineHeight": 21
        }
      },
      "verticalAlignment": 0
    }
  },
  "textBehaviour": 0
}