{
  "_class": "group",
  "do_objectID": "380E819B-E6FD-461D-B3D5-49684F5FD83C",
  "exportOptions": {
    "_class": "exportOptions",
    "do_objectID": "38B44EE3-889D-4C75-AAB1-18F3FC875D13",
    "exportFormats": [
    ],
    "includedLayerIds": [
    ],
    "layerOptions": 0,
    "shouldTrim": false
  },
  "frame": {
    "_class": "rect",
    "constrainProportions": false,
    "do_objectID": "70D40AA7-F9A5-4533-9BA4-AC57BCCE4538",
    "height": 8.000000000000071,
    "width": 7.999999999999829,
    "x": 88.00000000000006,
    "y": 127.9999999999999
  },
  "hasClickThrough": false,
  "isFlippedHorizontal": false,
  "isFlippedVertical": false,
  "isLocked": false,
  "isVisible": true,
  "layerListExpandedType": 0,
  "layers": [
    {
      "class": "shapeGroup",
      "id": "74F093FD-9FA7-45C9-B5CA-9AA758756E52"
    }
  ],
  "name": "p-link",
  "nameIsFixed": false,
  "resizingConstraint": 63,
  "resizingType": 0,
  "rotation": 0,
  "shouldBreakMaskChain": false,
  "style": {
    "_class": "style",
    "do_objectID": "5491A480-6264-4B4E-9B5D-93EC2D301363",
    "endDecorationType": 0,
    "fills": [
      {
        "_class": "fill",
        "color": {
          "_class": "color",
          "alpha": 1,
          "blue": 0,
          "green": 0,
          "red": 0
        },
        "fillType": 0,
        "isEnabled": true,
        "noiseIndex": 0,
        "noiseIntensity": 0,
        "patternFillType": 1,
        "patternTileScale": 1
      }
    ],
    "miterLimit": 10,
    "startDecorationType": 0
  }
}