{
  "_class": "symbolInstance",
  "do_objectID": "75FD1DD7-D6E9-46BB-8B72-6535B78F1E8E",
  "exportOptions": {
    "_class": "exportOptions",
    "do_objectID": "C83AFFA1-568F-4AF0-9450-D71CA801654B",
    "exportFormats": [
    ],
    "includedLayerIds": [
    ],
    "layerOptions": 0,
    "shouldTrim": false
  },
  "frame": {
    "_class": "rect",
    "constrainProportions": false,
    "do_objectID": "BDA86023-309F-4435-A176-136C8C435A16",
    "height": 16,
    "width": 128,
    "x": 51,
    "y": 133
  },
  "horizontalSpacing": 0,
  "isFlippedHorizontal": false,
  "isFlippedVertical": false,
  "isLocked": false,
  "isVisible": true,
  "layerListExpandedType": 0,
  "name": "hash_eth",
  "nameIsFixed": false,
  "overrideValues": [
  ],
  "resizingConstraint": 63,
  "resizingType": 0,
  "rotation": 0,
  "scale": 1,
  "shouldBreakMaskChain": false,
  "style": {
    "_class": "style",
    "do_objectID": "663DBF20-BB19-4952-A9E8-380AFDF8984E",
    "endDecorationType": 0,
    "miterLimit": 10,
    "startDecorationType": 0
  },
  "symbolID": "27E83CEB-E404-496E-B4AE-8F0817AE5304",
  "verticalSpacing": 0
}