{
  "_class": "shapeGroup",
  "clippingMaskMode": 0,
  "do_objectID": "1BD33480-27C5-4C93-A7D0-6A87BC88B8D7",
  "exportOptions": {
    "_class": "exportOptions",
    "exportFormats": [
    ],
    "includedLayerIds": [
    ],
    "layerOptions": 0,
    "shouldTrim": false
  },
  "frame": {
    "_class": "rect",
    "constrainProportions": false,
    "do_objectID": "1BD393ED-A29C-4B1C-AA12-D9464611B5C7",
    "height": 12,
    "width": 18,
    "x": 3,
    "y": 6
  },
  "hasClickThrough": false,
  "hasClippingMask": false,
  "isFlippedHorizontal": false,
  "isFlippedVertical": false,
  "isLocked": false,
  "isVisible": true,
  "layerListExpandedType": 0,
  "layers": [
    {
      "class": "shapePath",
      "id": "41BF2BF0-9675-4417-8599-0CC5C7EFEB99"
    },
    {
      "class": "shapePath",
      "id": "001C4218-B36E-423D-B4B6-656551FEEF74"
    },
    {
      "class": "shapePath",
      "id": "784C7602-93C5-498C-B15A-D78F11549389"
    }
  ],
  "name": "Shape",
  "nameIsFixed": false,
  "resizingConstraint": 45,
  "resizingType": 3,
  "rotation": 0,
  "shouldBreakMaskChain": false,
  "style": {
    "_class": "style",
    "do_objectID": "FF17EC63-408D-4EFC-96CD-3F8805C7F4A7",
    "endDecorationType": 0,
    "fills": [
      {
        "_class": "fill",
        "color": {
          "_class": "color",
          "alpha": 1,
          "blue": 0,
          "green": 0,
          "red": 0
        },
        "fillType": 0,
        "isEnabled": true,
        "noiseIndex": 0,
        "noiseIntensity": 0,
        "patternFillType": 0,
        "patternTileScale": 1
      }
    ],
    "miterLimit": 10,
    "sharedObjectID": "DC56376C-8162-4E24-BB3C-91C5B43AD324",
    "startDecorationType": 0
  },
  "windingRule": 1
}