{
  "_class": "shapePath",
  "booleanOperation": -1,
  "do_objectID": "7432108C-BF03-4F69-9866-AF001D36E77B",
  "edited": true,
  "exportOptions": {
    "_class": "exportOptions",
    "do_objectID": "20FA169E-624F-4EF2-9CD6-7AB568333DD2",
    "exportFormats": [
    ],
    "includedLayerIds": [
    ],
    "layerOptions": 0,
    "shouldTrim": false
  },
  "frame": {
    "_class": "rect",
    "constrainProportions": false,
    "do_objectID": "02E282A5-E523-4DE5-AF81-14B7AAE44B04",
    "height": 1,
    "width": 999.999999999999,
    "x": 0,
    "y": 0
  },
  "isClosed": true,
  "isFlippedHorizontal": false,
  "isFlippedVertical": false,
  "isLocked": false,
  "isVisible": true,
  "layerListExpandedType": 0,
  "name": "Path",
  "nameIsFixed": false,
  "pointRadiusBehaviour": 1,
  "points": [
    {
      "_class": "curvePoint",
      "cornerRadius": 0,
      "curveFrom": "{1, 0}",
      "curveMode": 1,
      "curveTo": "{1, 0}",
      "hasCurveFrom": false,
      "hasCurveTo": false,
      "point": "{1, 0}"
    },
    {
      "_class": "curvePoint",
      "cornerRadius": 0,
      "curveFrom": "{0, 5.6843418860808015e-14}",
      "curveMode": 1,
      "curveTo": "{0, 5.6843418860808015e-14}",
      "hasCurveFrom": false,
      "hasCurveTo": false,
      "point": "{0, 5.6843418860808015e-14}"
    }
  ],
  "resizingConstraint": 63,
  "resizingType": 0,
  "rotation": 0,
  "shouldBreakMaskChain": false
}