{
  "_class": "shapeGroup",
  "clippingMaskMode": 0,
  "do_objectID": "96EAC56A-0B86-4231-8161-6644821D38B1",
  "exportOptions": {
    "_class": "exportOptions",
    "do_objectID": "1C8AA190-E527-4EEC-94D4-8852ADD91923",
    "exportFormats": [
    ],
    "includedLayerIds": [
    ],
    "layerOptions": 0,
    "shouldTrim": false
  },
  "frame": {
    "_class": "rect",
    "constrainProportions": false,
    "do_objectID": "7CA0F7DB-1DAB-4285-AF7E-2E83D1227538",
    "height": 27,
    "width": 647,
    "x": 0,
    "y": 0.5
  },
  "hasClickThrough": false,
  "hasClippingMask": false,
  "isFlippedHorizontal": false,
  "isFlippedVertical": false,
  "isLocked": false,
  "isVisible": true,
  "layerListExpandedType": 0,
  "layers": [
    {
      "class": "rectangle",
      "id": "C129D435-4286-4271-9377-EEE904A795F5"
    }
  ],
  "name": "Rectangle",
  "nameIsFixed": false,
  "resizingConstraint": 63,
  "resizingType": 0,
  "rotation": 0,
  "shouldBreakMaskChain": false,
  "style": {
    "_class": "style",
    "borders": [
      {
        "_class": "border",
        "color": {
          "_class": "color",
          "alpha": 1,
          "blue": 0,
          "green": 0,
          "red": 0
        },
        "fillType": 0,
        "isEnabled": false,
        "position": 2,
        "thickness": 1
      }
    ],
    "do_objectID": "A4C740CB-4073-46E0-B678-B3DE76AEDFFB",
    "endDecorationType": 0,
    "fills": [
      {
        "_class": "fill",
        "color": {
          "_class": "color",
          "alpha": 1,
          "blue": 0.2588235294117647,
          "green": 0.2196078431372549,
          "red": 0.1803921568627451
        },
        "fillType": 0,
        "isEnabled": true,
        "noiseIndex": 0,
        "noiseIntensity": 0,
        "patternFillType": 1,
        "patternTileScale": 1
      }
    ],
    "miterLimit": 10,
    "shadows": [
      {
        "_class": "shadow",
        "blurRadius": 11,
        "color": {
          "_class": "color",
          "alpha": 0.08421082427536232,
          "blue": 0,
          "green": 0,
          "red": 0
        },
        "contextSettings": {
          "_class": "graphicsContextSettings",
          "blendMode": 0,
          "opacity": 1
        },
        "isEnabled": true,
        "offsetX": 4,
        "offsetY": 3,
        "spread": 0
      }
    ],
    "sharedObjectID": "01F067F5-40C9-4F9F-AE52-0DDFDF6C0DC1",
    "startDecorationType": 0
  },
  "windingRule": 1
}