{
  "_class": "shapeGroup",
  "clippingMaskMode": 0,
  "do_objectID": "96F6610A-5596-4CD4-813E-1F19538422DC",
  "exportOptions": {
    "_class": "exportOptions",
    "do_objectID": "F6B7E205-AB42-4A50-A7C4-8C1C70E48FF3",
    "exportFormats": [
    ],
    "includedLayerIds": [
    ],
    "layerOptions": 0,
    "shouldTrim": false
  },
  "frame": {
    "_class": "rect",
    "constrainProportions": false,
    "do_objectID": "CE58145E-D1A5-46A6-BA9C-7581E26F0C5A",
    "height": 159,
    "width": 2,
    "x": 704.1666666666788,
    "y": 0.5
  },
  "hasClickThrough": false,
  "hasClippingMask": false,
  "isFlippedHorizontal": false,
  "isFlippedVertical": false,
  "isLocked": false,
  "isVisible": true,
  "layerListExpandedType": 1,
  "layers": [
    {
      "class": "shapePath",
      "id": "AA0C6BCC-D8C2-48BD-BEC6-602C6097EB59"
    }
  ],
  "name": "Line 2",
  "nameIsFixed": false,
  "resizingConstraint": 63,
  "resizingType": 0,
  "rotation": 0,
  "shouldBreakMaskChain": false,
  "style": {
    "_class": "style",
    "borderOptions": {
      "_class": "borderOptions",
      "dashPattern": [
      ],
      "do_objectID": "550B6EA5-80C9-4BBD-B70A-58D54DF2C997",
      "isEnabled": false,
      "lineCapStyle": 2,
      "lineJoinStyle": 0
    },
    "borders": [
      {
        "_class": "border",
        "color": {
          "_class": "color",
          "alpha": 1,
          "blue": 0.592,
          "green": 0.592,
          "red": 0.592
        },
        "fillType": 0,
        "isEnabled": true,
        "position": 0,
        "thickness": 0.3
      }
    ],
    "do_objectID": "0520647D-AA83-4880-B3E4-2A058597C1B0",
    "endDecorationType": 0,
    "fills": [
      {
        "_class": "fill",
        "color": {
          "_class": "color",
          "alpha": 1,
          "blue": 0.847,
          "green": 0.847,
          "red": 0.847
        },
        "fillType": 0,
        "isEnabled": false,
        "noiseIndex": 0,
        "noiseIntensity": 0,
        "patternFillType": 1,
        "patternTileScale": 1
      }
    ],
    "miterLimit": 10,
    "startDecorationType": 0
  },
  "windingRule": 1
}