{
  "_class": "shapePath",
  "booleanOperation": -1,
  "do_objectID": "8C4534CC-55C8-4AAC-9190-599C82B63681",
  "edited": true,
  "exportOptions": {
    "_class": "exportOptions",
    "do_objectID": "E8BC3097-AEAE-4CDD-9D6A-06246D8A53B9",
    "exportFormats": [
    ],
    "includedLayerIds": [
    ],
    "layerOptions": 0,
    "shouldTrim": false
  },
  "frame": {
    "_class": "rect",
    "constrainProportions": false,
    "do_objectID": "FAF34791-9EB5-4119-9E93-172F9EB272E9",
    "height": 1,
    "width": 590.0000000000007,
    "x": -2.273736754432321e-13,
    "y": 0
  },
  "isClosed": true,
  "isFlippedHorizontal": false,
  "isFlippedVertical": false,
  "isLocked": false,
  "isVisible": true,
  "layerListExpandedType": 0,
  "name": "Path",
  "nameIsFixed": false,
  "pointRadiusBehaviour": 1,
  "points": [
    {
      "_class": "curvePoint",
      "cornerRadius": 0,
      "curveFrom": "{1, 0}",
      "curveMode": 1,
      "curveTo": "{1, 0}",
      "hasCurveFrom": false,
      "hasCurveTo": false,
      "point": "{1, 0}"
    },
    {
      "_class": "curvePoint",
      "cornerRadius": 0,
      "curveFrom": "{0, 2.8421709430404007e-14}",
      "curveMode": 1,
      "curveTo": "{0, 2.8421709430404007e-14}",
      "hasCurveFrom": false,
      "hasCurveTo": false,
      "point": "{0, 2.8421709430404007e-14}"
    }
  ],
  "resizingConstraint": 63,
  "resizingType": 0,
  "rotation": 0,
  "shouldBreakMaskChain": false
}