{
  "_class": "group",
  "do_objectID": "A4409FAA-9117-4708-A8DB-837CB6D0B4A6",
  "exportOptions": {
    "_class": "exportOptions",
    "do_objectID": "956A3674-1F0D-4C5F-AE46-CAAEE2258B64",
    "exportFormats": [
    ],
    "includedLayerIds": [
    ],
    "layerOptions": 0,
    "shouldTrim": false
  },
  "frame": {
    "_class": "rect",
    "constrainProportions": false,
    "do_objectID": "F9815DC7-9740-4CF2-9C5C-B82DE7114ED2",
    "height": 296,
    "width": 17,
    "x": 662,
    "y": 1653.333333333336
  },
  "hasClickThrough": false,
  "isFlippedHorizontal": false,
  "isFlippedVertical": false,
  "isLocked": false,
  "isVisible": true,
  "layerListExpandedType": 0,
  "layers": [
    {
      "class": "symbolInstance",
      "id": "63D71DF2-F20A-41BF-B9FE-ACCAE7EA1EA9"
    },
    {
      "class": "symbolInstance",
      "id": "3231AFF4-F575-4845-9474-98F929EAFF69"
    },
    {
      "class": "symbolInstance",
      "id": "EB31F095-1018-4387-A692-9D6B73BC0A69"
    },
    {
      "class": "symbolInstance",
      "id": "1708BCDD-DDC6-48C3-B798-60D7C81F6BC8"
    },
    {
      "class": "symbolInstance",
      "id": "3D2ED496-F52F-4374-861E-0990265015AD"
    },
    {
      "class": "symbolInstance",
      "id": "8768FEB8-3889-4FC8-A02A-C365FBD5C83B"
    },
    {
      "class": "symbolInstance",
      "id": "8AD50B96-9310-4231-9507-6FC90D727FF9"
    },
    {
      "class": "symbolInstance",
      "id": "1F6B554E-B3C6-4B0F-B2C7-1D8C39D08F4E"
    }
  ],
  "name": "Arrow",
  "nameIsFixed": true,
  "resizingConstraint": 63,
  "resizingType": 0,
  "rotation": 0,
  "shouldBreakMaskChain": false,
  "style": {
    "_class": "style",
    "do_objectID": "712B101F-BFD7-4589-97B5-019F1AFD01B9",
    "endDecorationType": 0,
    "miterLimit": 10,
    "startDecorationType": 0
  }
}